supercut/__init__.py
supercut/ffmpeg.py
supercut/mlt.py
supercut/subtitles.py
supercut/supercut.py
supercut/vlc.py
supercut-0.4.0.dist-info/LICENSE
supercut-0.4.0.dist-info/METADATA
supercut-0.4.0.dist-info/WHEEL
supercut-0.4.0.dist-info/entry_points.txt
supercut-0.4.0.dist-info/RECORD
