Metadata-Version: 2.1
Name: supercut
Version: 0.4.0
Summary: Subtitle-based automatic supercut creation
License: MIT
Author: Tamir Bahar
Requires-Python: >=3.11,<4.0
Classifier: License :: OSI Approved :: MIT License
Classifier: Programming Language :: Python :: 3
Classifier: Programming Language :: Python :: 3.11
Classifier: Programming Language :: Python :: 3.12
Requires-Dist: attrs (>=23.2.0,<24.0.0)
Requires-Dist: diskcache (>=5.6.3,<6.0.0)
Requires-Dist: more-itertools (>=10.2.0,<11.0.0)
Requires-Dist: pysubs2 (>=1.6.1,<2.0.0)
Requires-Dist: rich (>=13.7.0,<14.0.0)
Requires-Dist: typer (>=0.9.0,<0.10.0)
